jirafs_list_table/__init__.py
jirafs_list_table/plugin.py
jirafs_list_table-1.0.1.dist-info/LICENSE
jirafs_list_table-1.0.1.dist-info/METADATA
jirafs_list_table-1.0.1.dist-info/WHEEL
jirafs_list_table-1.0.1.dist-info/entry_points.txt
jirafs_list_table-1.0.1.dist-info/top_level.txt
jirafs_list_table-1.0.1.dist-info/RECORD
