Metadata-Version: 2.1
Name: jirafs-list-table
Version: 1.0.1
Summary: Make simple tables in JIRA more easily by using a simple list-based syntax.
Home-page: https://github.com/coddingtonbear/jirafs-list-table
Author: Adam Coddington
Author-email: me@adamcoddington.net
License: UNKNOWN
Platform: UNKNOWN
Classifier: License :: OSI Approved :: MIT License
Classifier: Operating System :: OS Independent
Classifier: Programming Language :: Python :: 3
Requires-Dist: six
